johnsnowlabs/__init__.py
johnsnowlabs/finance.py
johnsnowlabs/lab.py
johnsnowlabs/legal.py
johnsnowlabs/medical.py
johnsnowlabs/nlp.py
johnsnowlabs/settings.py
johnsnowlabs/visual.py
johnsnowlabs/viz.py
johnsnowlabs/abstract_base/__init__.py
johnsnowlabs/abstract_base/base_enum.py
johnsnowlabs/abstract_base/lib_resolver.py
johnsnowlabs/abstract_base/pydantic_model.py
johnsnowlabs/abstract_base/software_product.py
johnsnowlabs/auto_install/__init__.py
johnsnowlabs/auto_install/install_flow.py
johnsnowlabs/auto_install/install_software.py
johnsnowlabs/auto_install/jsl_home.py
johnsnowlabs/auto_install/offline_install.py
johnsnowlabs/auto_install/softwares.py
johnsnowlabs/auto_install/databricks/__init__.py
johnsnowlabs/auto_install/databricks/dbfs.py
johnsnowlabs/auto_install/databricks/install_utils.py
johnsnowlabs/auto_install/databricks/work_utils.py
johnsnowlabs/auto_install/emr/__init__.py
johnsnowlabs/auto_install/emr/enums.py
johnsnowlabs/auto_install/emr/errors.py
johnsnowlabs/auto_install/emr/install_utils.py
johnsnowlabs/auto_install/emr/s3_utils.py
johnsnowlabs/auto_install/emr/work_utils.py
johnsnowlabs/auto_install/health_checks/__init__.py
johnsnowlabs/auto_install/health_checks/hc_test.py
johnsnowlabs/auto_install/health_checks/nlp_test.py
johnsnowlabs/auto_install/health_checks/ocr_test.py
johnsnowlabs/auto_install/health_checks/report.py
johnsnowlabs/auto_install/lib_resolvers/__init__.py
johnsnowlabs/auto_install/lib_resolvers/hc_installer.py
johnsnowlabs/auto_install/lib_resolvers/nlp_installer.py
johnsnowlabs/auto_install/lib_resolvers/ocr_installer.py
johnsnowlabs/py_models/__init__.py
johnsnowlabs/py_models/install_info.py
johnsnowlabs/py_models/jsl_secrets.py
johnsnowlabs/py_models/lib_version.py
johnsnowlabs/py_models/license_info.py
johnsnowlabs/py_models/primitive.py
johnsnowlabs/py_models/url_dependency.py
johnsnowlabs/utils/__init__.py
johnsnowlabs/utils/enums.py
johnsnowlabs/utils/env_utils.py
johnsnowlabs/utils/file_utils.py
johnsnowlabs_by_kshitiz-5.0.1.dist-info/LICENSE
johnsnowlabs_by_kshitiz-5.0.1.dist-info/METADATA
johnsnowlabs_by_kshitiz-5.0.1.dist-info/WHEEL
johnsnowlabs_by_kshitiz-5.0.1.dist-info/top_level.txt
johnsnowlabs_by_kshitiz-5.0.1.dist-info/RECORD
